ingestion/__init__.py
ingestion/config/__init__.py
ingestion/config/feed.py
ingestion/config/model.py
ingestion/config/parser.py
ingestion/storage/__init__.py
ingestion/storage/bigquery/__init__.py
ingestion/storage/bigquery/utils.py
ingestion/storage/gcs/__init__.py
ingestion/storage/gcs/utils.py
src/__init__.py
src/ingestion/__init__.py
src/ingestion/config/__init__.py
src/ingestion/config/feed.py
src/ingestion/config/model.py
src/ingestion/config/parser.py
src/ingestion/storage/__init__.py
src/ingestion/storage/bigquery/__init__.py
src/ingestion/storage/bigquery/utils.py
src/ingestion/storage/gcs/__init__.py
src/ingestion/storage/gcs/utils.py
gcp_data_ingestion-1.0.24.dist-info/LICENSE
gcp_data_ingestion-1.0.24.dist-info/METADATA
gcp_data_ingestion-1.0.24.dist-info/WHEEL
gcp_data_ingestion-1.0.24.dist-info/top_level.txt
gcp_data_ingestion-1.0.24.dist-info/RECORD
