Metadata-Version: 2.1
Name: gcp-data-ingestion
Version: 1.0.24
Summary: Utility Functions for Data Ingestion in GCP
Home-page: https://github.com/sreeraaman/data-ingestion
Author: Sriraman Gopalan
Author-email: sreeraaman@gmail.com
License: UNKNOWN
Platform: UNKNOWN
Requires-Python: >=3.8
Requires-Dist: google-cloud-storage
Requires-Dist: google-cloud-bigquery
Requires-Dist: PyYAML
Requires-Dist: pandas-gbq
Requires-Dist: gcsfs
Requires-Dist: pytest
